w2n_n2w/__init__.py
w2n_n2w/converter.py
w2n_n2w/decorators.py
w2n_n2w/test.py
w2n_n2w/units.py
w2n_n2w-0.1.0.dist-info/WHEEL
w2n_n2w-0.1.0.dist-info/entry_points.txt
w2n_n2w-0.1.0.dist-info/METADATA
w2n_n2w-0.1.0.dist-info/RECORD
