Metadata-Version: 2.3
Name: w2n-n2w
Version: 0.1.0
Summary: Convert numbers to words and vice versa
Author: VipulSingh2
Author-email: VipulSingh2 <v.ipulsingh592005@gmail.com>
Requires-Python: >=3.12
